{"dokid": 551671, "minid": 60, "orgid": 891, "mindat": 20251231, "minjust": "60:20251231:1975/45381", "minnum": "1975/45381", "n_vlas": 836, "nazva": "Про встановлення вимог щодо запровадження постачальниками заходів безпеки відповідно до рівня ризику, пов'язаного з постачанням товарів, робіт і послуг власникам або розпорядникам інформаційно-комунікаційних систем, в яких обробляються державні інформаційні ресурси або службова інформація та інформація, що становить державну таємницю, об'єктів критичної інформаційної інфраструктури", "npix": 2, "nreg": "z1975-25", "num": 158, "org": 891, "organs": "891:20251217:836", "orgdat": 20251217, "orgnum": 836, "poddat": 20251217, "pridat": 20251217, "status": 5, "typ": 9, "types": "9|145|205|25"}