{"dokid": 551699, "minid": 60, "orgid": 1359, "mindat": 20251224, "minjust": "60:20251224:1941/45347", "minnum": "1941/45347", "n_vlas": 2886, "nazva": "Про затвердження Спеціальних вимог до відбору зразків, а також методів (методик) проведення лабораторних досліджень (випробувань) для окремих груп матеріалів і предметів, призначених для контакту з харчовими продуктами", "npix": 2, "nreg": "z1941-25", "num": 168, "org": 1359, "organs": "1359:20251209:2886", "orgdat": 20251209, "orgnum": 2886, "poddat": 20251209, "pridat": 20251209, "status": 5, "typ": 9, "types": "9|145|104"}