{"dokid": 551693, "orgid": 1, "minjust": "", "n_vlas": "4683-IX", "nazva": "Про внесення змін до Закону України \"Про загальнообов'язкове державне соціальне страхування\" щодо удосконалення порядку видачі, продовження та контролю за обґрунтованістю видачі листків непрацездатності та документів, що є підставою для їх формування", "npix": 2, "nreg": "4683-20", "num": 212, "org": 1, "organs": "1:20251105:4683-IX", "orgdat": 20251105, "orgnum": "4683-IX", "poddat": 20251105, "pridat": 20251105, "status": 2, "typ": 1, "types": 1}